{"params":{"limit":10,"offset":110,"order":"_played_at","identity_id":1031800,"game_type":"1v1","paginate":true,"page":12,"filter":"-graphs,match(-replays,-map,-map_url),entity(-summary,-minutes,-armies)","total":187},"provider":null,"stats":{},"collection":[{"id":2733609,"ended_at":"2013-04-07T19:08:22+00:00","winning_team":2,"category":"Ladder","game_type":"1v1","average_league":1,"duration_seconds":1560,"release_string":"2.0.7.25293","replays_count":1,"summaries_count":1,"expansion":1,"cobrand":null,"map_name":"Newkirk Precinct","entities":[{"id":8698605,"wpm":2.0,"apm":38.1153846153846,"spending_skill":2.21986258628525,"win":false,"race":"P","team":1,"color":"B4141E","race_macro":0.827130540932326,"sat_1_skill":null,"sat_2_skill":null,"sat_3_skill":null,"saturation_skill":null,"max_creep_spread":null,"identity":{"id":1031800,"type":"ESDB::Sc2::Identity","name":"Gingernut","provider_id":null,"provider_ident":null,"gateway":"eu","subregion":1,"bnet_id":665431,"matches_count":351,"hours_played":120.34944444444444,"profile_url":"http://eu.battle.net/sc2/en/profile/665431/1/Gingernut/","most_played_race":null,"current_highest_type":"1v1","current_highest_league":0,"current_highest_leaguerank":25,"current_league_1v1":0,"current_rank_1v1":25,"current_league_2v2":0,"current_rank_2v2":89,"current_league_3v3":0,"current_rank_3v3":59,"current_league_4v4":0,"current_rank_4v4":66,"achievement_points":2060,"season_games":0,"career_games":702,"portrait":"Unknown22","updated_at":"2014-01-03T18:42:17+00:00","queued":false,"most_played_gametype":"","stats":{"apm":{"avg":31.8509969847298},"wpm":{"avg":1.7225817495996}}},"spending_quotient":56.1846394351181,"stats":null},{"id":8698606,"wpm":1.03846153846154,"apm":52.7307692307692,"spending_skill":0.0,"win":true,"race":"T","team":2,"color":"0042FF","race_macro":null,"sat_1_skill":null,"sat_2_skill":null,"sat_3_skill":null,"saturation_skill":null,"max_creep_spread":null,"identity":{"id":1163747,"type":"ESDB::Sc2::Identity","name":"StormYxInori","provider_id":null,"provider_ident":null,"gateway":"eu","subregion":1,"bnet_id":3667443,"matches_count":8,"hours_played":2.4655555555555555,"profile_url":"http://eu.battle.net/sc2/en/profile/3667443/1/StormYxInori/","most_played_race":"t","current_highest_type":"1v1","current_highest_league":4,"current_highest_leaguerank":46,"current_league_1v1":4,"current_rank_1v1":46,"current_league_2v2":2,"current_rank_2v2":12,"current_league_3v3":null,"current_rank_3v3":null,"current_league_4v4":null,"current_rank_4v4":null,"achievement_points":1995,"season_games":98,"career_games":981,"portrait":"Unknown15","updated_at":"2013-07-10T00:26:08+00:00","queued":false,"most_played_gametype":"","stats":{"apm":{"avg":55.5464971031147},"wpm":{"avg":1.03846153846154}}},"spending_quotient":26.338928476787657,"stats":null}]},{"id":2733500,"ended_at":"2013-04-07T18:47:18+00:00","winning_team":1,"category":"Ladder","game_type":"1v1","average_league":1,"duration_seconds":281,"release_string":"2.0.7.25293","replays_count":2,"summaries_count":1,"expansion":1,"cobrand":null,"map_name":"Daybreak LE","entities":[{"id":8698333,"wpm":0.0,"apm":33.6,"spending_skill":null,"win":true,"race":"Z","team":1,"color":"B4141E","race_macro":0.0,"sat_1_skill":null,"sat_2_skill":null,"sat_3_skill":null,"saturation_skill":null,"max_creep_spread":null,"identity":{"id":1092524,"type":"ESDB::Sc2::Identity","name":"Shango","provider_id":null,"provider_ident":null,"gateway":"eu","subregion":1,"bnet_id":705174,"matches_count":5,"hours_played":1.275,"profile_url":"http://eu.battle.net/sc2/en/profile/705174/1/Shango/","most_played_race":"z","current_highest_type":"1v1","current_highest_league":1,"current_highest_leaguerank":53,"current_league_1v1":1,"current_rank_1v1":53,"current_league_2v2":2,"current_rank_2v2":49,"current_league_3v3":null,"current_rank_3v3":null,"current_league_4v4":null,"current_rank_4v4":null,"achievement_points":2345,"season_games":13,"career_games":1238,"portrait":"Kate Lockwell","updated_at":"2013-05-16T00:22:17+00:00","queued":false,"most_played_gametype":"","stats":{"apm":{"avg":23.9539682539682},"wpm":{"avg":0.99337748344371}}},"spending_quotient":87.95198170607765,"stats":null},{"id":8698334,"wpm":2.34875444839858,"apm":25.0,"spending_skill":null,"win":false,"race":"P","team":2,"color":"0042FF","race_macro":1.0,"sat_1_skill":null,"sat_2_skill":null,"sat_3_skill":null,"saturation_skill":null,"max_creep_spread":null,"identity":{"id":1031800,"type":"ESDB::Sc2::Identity","name":"Gingernut","provider_id":null,"provider_ident":null,"gateway":"eu","subregion":1,"bnet_id":665431,"matches_count":351,"hours_played":120.34944444444444,"profile_url":"http://eu.battle.net/sc2/en/profile/665431/1/Gingernut/","most_played_race":null,"current_highest_type":"1v1","current_highest_league":0,"current_highest_leaguerank":25,"current_league_1v1":0,"current_rank_1v1":25,"current_league_2v2":0,"current_rank_2v2":89,"current_league_3v3":0,"current_rank_3v3":59,"current_league_4v4":0,"current_rank_4v4":66,"achievement_points":2060,"season_games":0,"career_games":702,"portrait":"Unknown22","updated_at":"2014-01-03T18:42:17+00:00","queued":false,"most_played_gametype":"","stats":{"apm":{"avg":31.8509969847298},"wpm":{"avg":1.7225817495996}}},"spending_quotient":87.80243270947702,"stats":null}]},{"id":2733380,"ended_at":"2013-04-07T18:03:21+00:00","winning_team":1,"category":"Ladder","game_type":"1v1","average_league":1,"duration_seconds":1200,"release_string":"2.0.7.25293","replays_count":1,"summaries_count":1,"expansion":1,"cobrand":null,"map_name":"Newkirk Precinct","entities":[{"id":8698067,"wpm":2.04488778054863,"apm":31.8095238095238,"spending_skill":4.19268337915955,"win":true,"race":"P","team":1,"color":"B4141E","race_macro":0.996101205082066,"sat_1_skill":null,"sat_2_skill":null,"sat_3_skill":null,"saturation_skill":null,"max_creep_spread":null,"identity":{"id":1031800,"type":"ESDB::Sc2::Identity","name":"Gingernut","provider_id":null,"provider_ident":null,"gateway":"eu","subregion":1,"bnet_id":665431,"matches_count":351,"hours_played":120.34944444444444,"profile_url":"http://eu.battle.net/sc2/en/profile/665431/1/Gingernut/","most_played_race":null,"current_highest_type":"1v1","current_highest_league":0,"current_highest_leaguerank":25,"current_league_1v1":0,"current_rank_1v1":25,"current_league_2v2":0,"current_rank_2v2":89,"current_league_3v3":0,"current_rank_3v3":59,"current_league_4v4":0,"current_rank_4v4":66,"achievement_points":2060,"season_games":0,"career_games":702,"portrait":"Unknown22","updated_at":"2014-01-03T18:42:17+00:00","queued":false,"most_played_gametype":"","stats":{"apm":{"avg":31.8509969847298},"wpm":{"avg":1.7225817495996}}},"spending_quotient":69.54503323847118,"stats":null},{"id":8698068,"wpm":0.748129675810474,"apm":36.6,"spending_skill":0.0,"win":false,"race":"T","team":2,"color":"0042FF","race_macro":null,"sat_1_skill":null,"sat_2_skill":null,"sat_3_skill":null,"saturation_skill":null,"max_creep_spread":null,"identity":{"id":1163708,"type":"ESDB::Sc2::Identity","name":"Vay","provider_id":null,"provider_ident":null,"gateway":"eu","subregion":1,"bnet_id":3393739,"matches_count":1,"hours_played":0.33416666666666667,"profile_url":"http://eu.battle.net/sc2/en/profile/3393739/1/Vay/","most_played_race":"p","current_highest_type":"1v1","current_highest_league":1,"current_highest_leaguerank":31,"current_league_1v1":1,"current_rank_1v1":31,"current_league_2v2":null,"current_rank_2v2":null,"current_league_3v3":null,"current_rank_3v3":null,"current_league_4v4":null,"current_rank_4v4":null,"achievement_points":1340,"season_games":103,"career_games":133,"portrait":"Unknown10","updated_at":"2013-04-07T18:03:29+00:00","queued":false,"most_played_gametype":"","stats":{"apm":{"avg":36.6},"wpm":{"avg":0.748129675810474}}},"spending_quotient":28.468424778742104,"stats":null}]},{"id":2733136,"ended_at":"2013-04-07T17:40:38+00:00","winning_team":1,"category":"Ladder","game_type":"1v1","average_league":2,"duration_seconds":1369,"release_string":"2.0.7.25293","replays_count":1,"summaries_count":1,"expansion":1,"cobrand":null,"map_name":"Daybreak LE","entities":[{"id":8697486,"wpm":1.8353969410051,"apm":35.2608695652174,"spending_skill":0.0,"win":true,"race":"P","team":1,"color":"B4141E","race_macro":0.995835046891002,"sat_1_skill":null,"sat_2_skill":null,"sat_3_skill":null,"saturation_skill":null,"max_creep_spread":null,"identity":{"id":1031800,"type":"ESDB::Sc2::Identity","name":"Gingernut","provider_id":null,"provider_ident":null,"gateway":"eu","subregion":1,"bnet_id":665431,"matches_count":351,"hours_played":120.34944444444444,"profile_url":"http://eu.battle.net/sc2/en/profile/665431/1/Gingernut/","most_played_race":null,"current_highest_type":"1v1","current_highest_league":0,"current_highest_leaguerank":25,"current_league_1v1":0,"current_rank_1v1":25,"current_league_2v2":0,"current_rank_2v2":89,"current_league_3v3":0,"current_rank_3v3":59,"current_league_4v4":0,"current_rank_4v4":66,"achievement_points":2060,"season_games":0,"career_games":702,"portrait":"Unknown22","updated_at":"2014-01-03T18:42:17+00:00","queued":false,"most_played_gametype":"","stats":{"apm":{"avg":31.8509969847298},"wpm":{"avg":1.7225817495996}}},"spending_quotient":45.85649883391429,"stats":null},{"id":8697487,"wpm":0.611798980335033,"apm":63.3913043478261,"spending_skill":0.0,"win":false,"race":"T","team":2,"color":"0042FF","race_macro":null,"sat_1_skill":null,"sat_2_skill":null,"sat_3_skill":null,"saturation_skill":null,"max_creep_spread":null,"identity":{"id":970127,"type":"ESDB::Sc2::Identity","name":"Lush","provider_id":null,"provider_ident":null,"gateway":"eu","subregion":1,"bnet_id":3539028,"matches_count":22,"hours_played":5.794722222222222,"profile_url":"http://eu.battle.net/sc2/en/profile/3539028/1/Lush/","most_played_race":"p","current_highest_type":"1v1","current_highest_league":3,"current_highest_leaguerank":13,"current_league_1v1":3,"current_rank_1v1":13,"current_league_2v2":3,"current_rank_2v2":16,"current_league_3v3":null,"current_rank_3v3":null,"current_league_4v4":null,"current_rank_4v4":null,"achievement_points":1725,"season_games":814,"career_games":1669,"portrait":"Unknown23","updated_at":"2013-11-09T19:25:45+00:00","queued":false,"most_played_gametype":"","stats":{"apm":{"avg":62.2707231482949},"wpm":{"avg":1.1982020998258}}},"spending_quotient":35.48837428849569,"stats":null}]},{"id":2732997,"ended_at":"2013-04-07T17:15:12+00:00","winning_team":1,"category":"Ladder","game_type":"1v1","average_league":1,"duration_seconds":1294,"release_string":"2.0.7.25293","replays_count":1,"summaries_count":1,"expansion":1,"cobrand":null,"map_name":"Bel'Shir Vestige LE","entities":[{"id":8697149,"wpm":1.71032357473035,"apm":30.6818181818182,"spending_skill":0.0,"win":true,"race":"P","team":1,"color":"B4141E","race_macro":0.867028697676441,"sat_1_skill":null,"sat_2_skill":null,"sat_3_skill":null,"saturation_skill":null,"max_creep_spread":null,"identity":{"id":1031800,"type":"ESDB::Sc2::Identity","name":"Gingernut","provider_id":null,"provider_ident":null,"gateway":"eu","subregion":1,"bnet_id":665431,"matches_count":351,"hours_played":120.34944444444444,"profile_url":"http://eu.battle.net/sc2/en/profile/665431/1/Gingernut/","most_played_race":null,"current_highest_type":"1v1","current_highest_league":0,"current_highest_leaguerank":25,"current_league_1v1":0,"current_rank_1v1":25,"current_league_2v2":0,"current_rank_2v2":89,"current_league_3v3":0,"current_rank_3v3":59,"current_league_4v4":0,"current_rank_4v4":66,"achievement_points":2060,"season_games":0,"career_games":702,"portrait":"Unknown22","updated_at":"2014-01-03T18:42:17+00:00","queued":false,"most_played_gametype":"","stats":{"apm":{"avg":31.8509969847298},"wpm":{"avg":1.7225817495996}}},"spending_quotient":45.1409180251724,"stats":null},{"id":8697150,"wpm":0.970724191063174,"apm":43.8636363636364,"spending_skill":0.0,"win":false,"race":"Z","team":2,"color":"0042FF","race_macro":0.463069038287609,"sat_1_skill":null,"sat_2_skill":null,"sat_3_skill":null,"saturation_skill":null,"max_creep_spread":null,"identity":{"id":1163652,"type":"ESDB::Sc2::Identity","name":"Sajfer","provider_id":null,"provider_ident":null,"gateway":"eu","subregion":1,"bnet_id":248994,"matches_count":1,"hours_played":0.3605555555555556,"profile_url":"http://eu.battle.net/sc2/en/profile/248994/1/Sajfer/","most_played_race":"z","current_highest_type":"1v1","current_highest_league":1,"current_highest_leaguerank":7,"current_league_1v1":1,"current_rank_1v1":7,"current_league_2v2":null,"current_rank_2v2":null,"current_league_3v3":null,"current_rank_3v3":null,"current_league_4v4":null,"current_rank_4v4":null,"achievement_points":2020,"season_games":49,"career_games":115,"portrait":"Unknown12","updated_at":"2013-04-07T17:15:20+00:00","queued":false,"most_played_gametype":"","stats":{"apm":{"avg":null},"wpm":{"avg":null}}},"spending_quotient":34.69782947525107,"stats":null}]},{"id":2732922,"ended_at":"2013-04-07T16:57:31+00:00","winning_team":1,"category":"Ladder","game_type":"1v1","average_league":1,"duration_seconds":1059,"release_string":"2.0.7.25293","replays_count":1,"summaries_count":1,"expansion":1,"cobrand":null,"map_name":"Korhal City","entities":[{"id":8696916,"wpm":1.69971671388102,"apm":52.3333333333333,"spending_skill":0.0,"win":true,"race":"Z","team":1,"color":"B4141E","race_macro":0.399109131403118,"sat_1_skill":null,"sat_2_skill":null,"sat_3_skill":null,"saturation_skill":null,"max_creep_spread":null,"identity":{"id":1163639,"type":"ESDB::Sc2::Identity","name":"iConeOne","provider_id":null,"provider_ident":null,"gateway":"eu","subregion":1,"bnet_id":1342655,"matches_count":2,"hours_played":0.5119444444444444,"profile_url":"http://eu.battle.net/sc2/en/profile/1342655/1/iConeOne/","most_played_race":null,"current_highest_type":"1v1","current_highest_league":1,"current_highest_leaguerank":2,"current_league_1v1":1,"current_rank_1v1":2,"current_league_2v2":1,"current_rank_2v2":13,"current_league_3v3":0,"current_rank_3v3":45,"current_league_4v4":null,"current_rank_4v4":null,"achievement_points":2850,"season_games":0,"career_games":617,"portrait":"Baneling","updated_at":"2013-06-16T15:17:13+00:00","queued":false,"most_played_gametype":"","stats":{"apm":{"avg":null},"wpm":{"avg":null}}},"spending_quotient":46.771803515588715,"stats":null},{"id":8696917,"wpm":1.92634560906516,"apm":34.3888888888889,"spending_skill":2.73838690968474,"win":false,"race":"P","team":2,"color":"0042FF","race_macro":0.822191984276268,"sat_1_skill":null,"sat_2_skill":null,"sat_3_skill":null,"saturation_skill":null,"max_creep_spread":null,"identity":{"id":1031800,"type":"ESDB::Sc2::Identity","name":"Gingernut","provider_id":null,"provider_ident":null,"gateway":"eu","subregion":1,"bnet_id":665431,"matches_count":351,"hours_played":120.34944444444444,"profile_url":"http://eu.battle.net/sc2/en/profile/665431/1/Gingernut/","most_played_race":null,"current_highest_type":"1v1","current_highest_league":0,"current_highest_leaguerank":25,"current_league_1v1":0,"current_rank_1v1":25,"current_league_2v2":0,"current_rank_2v2":89,"current_league_3v3":0,"current_rank_3v3":59,"current_league_4v4":0,"current_rank_4v4":66,"achievement_points":2060,"season_games":0,"career_games":702,"portrait":"Unknown22","updated_at":"2014-01-03T18:42:17+00:00","queued":false,"most_played_gametype":"","stats":{"apm":{"avg":31.8509969847298},"wpm":{"avg":1.7225817495996}}},"spending_quotient":64.31524234502942,"stats":null}]},{"id":2724591,"ended_at":"2013-04-06T16:35:07+00:00","winning_team":2,"category":"Ladder","game_type":"1v1","average_league":1,"duration_seconds":1811,"release_string":"2.0.7.25293","replays_count":2,"summaries_count":1,"expansion":1,"cobrand":null,"map_name":"Akilon Wastes","entities":[{"id":8675585,"wpm":1.78906681391496,"apm":75.3,"spending_skill":4.27685623167023,"win":false,"race":"Z","team":1,"color":"B4141E","race_macro":0.546164321379936,"sat_1_skill":null,"sat_2_skill":null,"sat_3_skill":null,"saturation_skill":null,"max_creep_spread":null,"identity":{"id":613809,"type":"ESDB::Sc2::Identity","name":"Zylo","provider_id":null,"provider_ident":null,"gateway":"eu","subregion":1,"bnet_id":3369739,"matches_count":6,"hours_played":2.4916666666666667,"profile_url":"http://eu.battle.net/sc2/en/profile/3369739/1/Zylo/","most_played_race":"z","current_highest_type":"1v1","current_highest_league":0,"current_highest_leaguerank":33,"current_league_1v1":0,"current_rank_1v1":33,"current_league_2v2":0,"current_rank_2v2":92,"current_league_3v3":2,"current_rank_3v3":32,"current_league_4v4":0,"current_rank_4v4":72,"achievement_points":2875,"season_games":16,"career_games":940,"portrait":"Queen","updated_at":"2013-09-07T17:05:45+00:00","queued":false,"most_played_gametype":"","stats":{"apm":{"avg":80.4744733605887},"wpm":{"avg":1.78906681391496}}},"spending_quotient":61.063432252596385,"stats":null},{"id":8675586,"wpm":1.4246272777471,"apm":29.6129032258065,"spending_skill":0.0,"win":true,"race":"P","team":2,"color":"0042FF","race_macro":0.637066583518162,"sat_1_skill":null,"sat_2_skill":null,"sat_3_skill":null,"saturation_skill":null,"max_creep_spread":null,"identity":{"id":1031800,"type":"ESDB::Sc2::Identity","name":"Gingernut","provider_id":null,"provider_ident":null,"gateway":"eu","subregion":1,"bnet_id":665431,"matches_count":351,"hours_played":120.34944444444444,"profile_url":"http://eu.battle.net/sc2/en/profile/665431/1/Gingernut/","most_played_race":null,"current_highest_type":"1v1","current_highest_league":0,"current_highest_leaguerank":25,"current_league_1v1":0,"current_rank_1v1":25,"current_league_2v2":0,"current_rank_2v2":89,"current_league_3v3":0,"current_rank_3v3":59,"current_league_4v4":0,"current_rank_4v4":66,"achievement_points":2060,"season_games":0,"career_games":702,"portrait":"Unknown22","updated_at":"2014-01-03T18:42:17+00:00","queued":false,"most_played_gametype":"","stats":{"apm":{"avg":31.8509969847298},"wpm":{"avg":1.7225817495996}}},"spending_quotient":35.23566191592286,"stats":null}]},{"id":2724503,"ended_at":"2013-04-06T16:11:42+00:00","winning_team":1,"category":"Ladder","game_type":"1v1","average_league":1,"duration_seconds":503,"release_string":"2.0.7.25293","replays_count":2,"summaries_count":1,"expansion":1,"cobrand":null,"map_name":"Bel'Shir Vestige LE","entities":[{"id":8675351,"wpm":1.5506958250497,"apm":40.7777777777778,"spending_skill":1.85401130563106,"win":true,"race":"Z","team":1,"color":"B4141E","race_macro":0.703296703296703,"sat_1_skill":null,"sat_2_skill":null,"sat_3_skill":null,"saturation_skill":null,"max_creep_spread":null,"identity":{"id":365072,"type":"ESDB::Sc2::Identity","name":"Baal","provider_id":null,"provider_ident":null,"gateway":"eu","subregion":1,"bnet_id":1609775,"matches_count":3,"hours_played":0.7661111111111111,"profile_url":"http://eu.battle.net/sc2/en/profile/1609775/1/Baal/","most_played_race":"p","current_highest_type":"2v2","current_highest_league":0,"current_highest_leaguerank":19,"current_league_1v1":1,"current_rank_1v1":18,"current_league_2v2":0,"current_rank_2v2":19,"current_league_3v3":1,"current_rank_3v3":66,"current_league_4v4":0,"current_rank_4v4":16,"achievement_points":3485,"season_games":14,"career_games":443,"portrait":"Kate Lockwell","updated_at":"2013-09-21T20:07:44+00:00","queued":false,"most_played_gametype":"","stats":{"apm":{"avg":38.3339978805587},"wpm":{"avg":1.5506958250497}}},"spending_quotient":71.67758763625221,"stats":null},{"id":8675352,"wpm":2.02783300198807,"apm":26.2222222222222,"spending_skill":6.76125706345199,"win":false,"race":"P","team":2,"color":"0042FF","race_macro":1.0,"sat_1_skill":null,"sat_2_skill":null,"sat_3_skill":null,"saturation_skill":null,"max_creep_spread":null,"identity":{"id":1031800,"type":"ESDB::Sc2::Identity","name":"Gingernut","provider_id":null,"provider_ident":null,"gateway":"eu","subregion":1,"bnet_id":665431,"matches_count":351,"hours_played":120.34944444444444,"profile_url":"http://eu.battle.net/sc2/en/profile/665431/1/Gingernut/","most_played_race":null,"current_highest_type":"1v1","current_highest_league":0,"current_highest_leaguerank":25,"current_league_1v1":0,"current_rank_1v1":25,"current_league_2v2":0,"current_rank_2v2":89,"current_league_3v3":0,"current_rank_3v3":59,"current_league_4v4":0,"current_rank_4v4":66,"achievement_points":2060,"season_games":0,"career_games":702,"portrait":"Unknown22","updated_at":"2014-01-03T18:42:17+00:00","queued":false,"most_played_gametype":"","stats":{"apm":{"avg":31.8509969847298},"wpm":{"avg":1.7225817495996}}},"spending_quotient":82.52491443278353,"stats":null}]},{"id":2724460,"ended_at":"2013-04-06T16:04:54+00:00","winning_team":1,"category":"Ladder","game_type":"1v1","average_league":1,"duration_seconds":398,"release_string":"2.0.7.25293","replays_count":2,"summaries_count":1,"expansion":1,"cobrand":null,"map_name":"Bel'Shir Vestige LE","entities":[{"id":8675253,"wpm":0.452261306532663,"apm":61.0,"spending_skill":6.85076168497526,"win":true,"race":"Z","team":1,"color":"B4141E","race_macro":0.0,"sat_1_skill":null,"sat_2_skill":null,"sat_3_skill":null,"saturation_skill":null,"max_creep_spread":null,"identity":{"id":537853,"type":"ESDB::Sc2::Identity","name":"Eaglearchie","provider_id":null,"provider_ident":null,"gateway":"eu","subregion":1,"bnet_id":719906,"matches_count":8,"hours_played":3.0019444444444443,"profile_url":"http://eu.battle.net/sc2/en/profile/719906/1/Eaglearchie/","most_played_race":"p","current_highest_type":"2v2","current_highest_league":1,"current_highest_leaguerank":80,"current_league_1v1":0,"current_rank_1v1":2,"current_league_2v2":1,"current_rank_2v2":80,"current_league_3v3":1,"current_rank_3v3":95,"current_league_4v4":0,"current_rank_4v4":70,"achievement_points":1810,"season_games":203,"career_games":4164,"portrait":"Lenassa Dark Templar","updated_at":"2013-10-27T13:27:34+00:00","queued":false,"most_played_gametype":"","stats":{"apm":{"avg":38.3377516558463},"wpm":{"avg":0.832784273618582}}},"spending_quotient":91.87261575238162,"stats":null},{"id":8675254,"wpm":2.1105527638191,"apm":29.1428571428571,"spending_skill":5.90223864502577,"win":false,"race":"P","team":2,"color":"0042FF","race_macro":0.71793145998093,"sat_1_skill":null,"sat_2_skill":null,"sat_3_skill":null,"saturation_skill":null,"max_creep_spread":null,"identity":{"id":1031800,"type":"ESDB::Sc2::Identity","name":"Gingernut","provider_id":null,"provider_ident":null,"gateway":"eu","subregion":1,"bnet_id":665431,"matches_count":351,"hours_played":120.34944444444444,"profile_url":"http://eu.battle.net/sc2/en/profile/665431/1/Gingernut/","most_played_race":null,"current_highest_type":"1v1","current_highest_league":0,"current_highest_leaguerank":25,"current_league_1v1":0,"current_rank_1v1":25,"current_league_2v2":0,"current_rank_2v2":89,"current_league_3v3":0,"current_rank_3v3":59,"current_league_4v4":0,"current_rank_4v4":66,"achievement_points":2060,"season_games":0,"career_games":702,"portrait":"Unknown22","updated_at":"2014-01-03T18:42:17+00:00","queued":false,"most_played_gametype":"","stats":{"apm":{"avg":31.8509969847298},"wpm":{"avg":1.7225817495996}}},"spending_quotient":88.48265197394929,"stats":null}]},{"id":2724447,"ended_at":"2013-04-06T15:58:48+00:00","winning_team":2,"category":"Ladder","game_type":"1v1","average_league":1,"duration_seconds":860,"release_string":"2.0.7.25293","replays_count":2,"summaries_count":1,"expansion":1,"cobrand":null,"map_name":"Neo Planet S LE","entities":[{"id":8675224,"wpm":2.09302325581395,"apm":30.6,"spending_skill":3.07893185877142,"win":false,"race":"P","team":1,"color":"B4141E","race_macro":0.958188838879461,"sat_1_skill":null,"sat_2_skill":null,"sat_3_skill":null,"saturation_skill":null,"max_creep_spread":null,"identity":{"id":1031800,"type":"ESDB::Sc2::Identity","name":"Gingernut","provider_id":null,"provider_ident":null,"gateway":"eu","subregion":1,"bnet_id":665431,"matches_count":351,"hours_played":120.34944444444444,"profile_url":"http://eu.battle.net/sc2/en/profile/665431/1/Gingernut/","most_played_race":null,"current_highest_type":"1v1","current_highest_league":0,"current_highest_leaguerank":25,"current_league_1v1":0,"current_rank_1v1":25,"current_league_2v2":0,"current_rank_2v2":89,"current_league_3v3":0,"current_rank_3v3":59,"current_league_4v4":0,"current_rank_4v4":66,"achievement_points":2060,"season_games":0,"career_games":702,"portrait":"Unknown22","updated_at":"2014-01-03T18:42:17+00:00","queued":false,"most_played_gametype":"","stats":{"apm":{"avg":31.8509969847298},"wpm":{"avg":1.7225817495996}}},"spending_quotient":67.04543881718809,"stats":null},{"id":8675225,"wpm":1.3953488372093,"apm":24.0666666666667,"spending_skill":2.65774318599739,"win":true,"race":"P","team":2,"color":"0042FF","race_macro":0.748927200697577,"sat_1_skill":null,"sat_2_skill":null,"sat_3_skill":null,"saturation_skill":null,"max_creep_spread":null,"identity":{"id":791563,"type":"ESDB::Sc2::Identity","name":"Shidaya","provider_id":null,"provider_ident":null,"gateway":"eu","subregion":1,"bnet_id":418779,"matches_count":5,"hours_played":1.696388888888889,"profile_url":"http://eu.battle.net/sc2/en/profile/418779/1/Shidaya/","most_played_race":"p","current_highest_type":"1v1","current_highest_league":1,"current_highest_leaguerank":83,"current_league_1v1":1,"current_rank_1v1":83,"current_league_2v2":1,"current_rank_2v2":28,"current_league_3v3":null,"current_rank_3v3":null,"current_league_4v4":null,"current_rank_4v4":null,"achievement_points":1495,"season_games":50,"career_games":1047,"portrait":"Unknown41","updated_at":"2013-05-27T14:46:00+00:00","queued":false,"most_played_gametype":"","stats":{"apm":{"avg":23.0757142857143},"wpm":{"avg":1.3953488372093}}},"spending_quotient":65.78651942073174,"stats":null}]}]}