{"params":{"limit":10,"offset":30,"order":"_played_at","identity_id":1161842,"game_type":"1v1","paginate":true,"page":4,"filter":"-graphs,match(-replays,-map,-map_url),entity(-summary,-minutes,-armies)","total":132},"provider":null,"stats":{},"collection":[{"id":4420254,"ended_at":"2013-11-27T19:34:02+00:00","winning_team":2,"category":"Ladder","game_type":"1v1","average_league":0,"duration_seconds":1084,"release_string":"2.0.11.26825","replays_count":1,"summaries_count":0,"expansion":1,"cobrand":null,"map_name":"Frost LE","entities":[{"id":13182308,"wpm":null,"apm":50.7564575645756,"spending_skill":1.83125173190278,"win":false,"race":"Z","team":1,"color":"B4141E","race_macro":0.671600574395228,"sat_1_skill":2.0,"sat_2_skill":0.0,"sat_3_skill":0.0,"saturation_skill":0.0,"max_creep_spread":5.87628865979381,"identity":{"id":1161842,"type":"ESDB::Sc2::Identity","name":"Baconator","provider_id":null,"provider_ident":null,"gateway":"eu","subregion":1,"bnet_id":3640351,"matches_count":256,"hours_played":87.88027777777778,"profile_url":"http://eu.battle.net/sc2/en/profile/3640351/1/Baconator/","most_played_race":"z","current_highest_type":"1v1","current_highest_league":1,"current_highest_leaguerank":91,"current_league_1v1":1,"current_rank_1v1":91,"current_league_2v2":0,"current_rank_2v2":82,"current_league_3v3":0,"current_rank_3v3":63,"current_league_4v4":0,"current_rank_4v4":66,"achievement_points":290,"season_games":1,"career_games":280,"portrait":"Unknown59","updated_at":"2014-01-03T18:42:11+00:00","queued":false,"most_played_gametype":"","stats":{"apm":{"avg":53.676660855791},"wpm":{"avg":1.32040768344748}}},"spending_quotient":61.868345419023086,"stats":{"entity_id":13182308,"highest_league":0,"base_2":264,"miningbase_2":264,"base_3":1036,"miningbase_3":536,"saturation_1":460,"mineral_saturation_1":260,"gas_saturation_1":440,"worker22x_1":430,"saturation_2":null,"mineral_saturation_2":null,"gas_saturation_2":null,"worker22x_2":null,"saturation_3":null,"mineral_saturation_3":null,"gas_saturation_3":null,"worker22x_3":null}},{"id":13182312,"wpm":null,"apm":51.309963099631,"spending_skill":1.32131278720962,"win":true,"race":"P","team":2,"color":"0042FF","race_macro":0.533867200533867,"sat_1_skill":5.0,"sat_2_skill":3.0,"sat_3_skill":null,"saturation_skill":3.0,"max_creep_spread":null,"identity":{"id":780650,"type":"ESDB::Sc2::Identity","name":"Tener","provider_id":null,"provider_ident":null,"gateway":"eu","subregion":2,"bnet_id":19743,"matches_count":3,"hours_played":0.9402777777777778,"profile_url":"http://eu.battle.net/sc2/en/profile/19743/2/Tener/","most_played_race":"p","current_highest_type":"1v1","current_highest_league":1,"current_highest_leaguerank":25,"current_league_1v1":1,"current_rank_1v1":25,"current_league_2v2":1,"current_rank_2v2":16,"current_league_3v3":null,"current_rank_3v3":null,"current_league_4v4":null,"current_rank_4v4":null,"achievement_points":835,"season_games":87,"career_games":1464,"portrait":"Void Ray","updated_at":"2013-12-13T20:16:31+00:00","queued":false,"most_played_gametype":"","stats":{"apm":{"avg":49.1692888625976},"wpm":{"avg":1.29930394431555}}},"spending_quotient":60.46477310058083,"stats":{"entity_id":13182312,"highest_league":1,"base_2":337,"miningbase_2":337,"base_3":null,"miningbase_3":null,"saturation_1":410,"mineral_saturation_1":210,"gas_saturation_1":680,"worker22x_1":310,"saturation_2":null,"mineral_saturation_2":580,"gas_saturation_2":null,"worker22x_2":null,"saturation_3":null,"mineral_saturation_3":null,"gas_saturation_3":null,"worker22x_3":null}}]},{"id":4420259,"ended_at":"2013-11-27T19:19:39+00:00","winning_team":2,"category":"Ladder","game_type":"1v1","average_league":0,"duration_seconds":1311,"release_string":"2.0.11.26825","replays_count":1,"summaries_count":0,"expansion":1,"cobrand":null,"map_name":"Alterzim Stronghold TE","entities":[{"id":13182321,"wpm":null,"apm":60.0,"spending_skill":0.213700494767678,"win":false,"race":"Z","team":1,"color":"B4141E","race_macro":0.636954561005194,"sat_1_skill":0.0,"sat_2_skill":0.0,"sat_3_skill":null,"saturation_skill":0.0,"max_creep_spread":7.28,"identity":{"id":1161842,"type":"ESDB::Sc2::Identity","name":"Baconator","provider_id":null,"provider_ident":null,"gateway":"eu","subregion":1,"bnet_id":3640351,"matches_count":256,"hours_played":87.88027777777778,"profile_url":"http://eu.battle.net/sc2/en/profile/3640351/1/Baconator/","most_played_race":"z","current_highest_type":"1v1","current_highest_league":1,"current_highest_leaguerank":91,"current_league_1v1":1,"current_rank_1v1":91,"current_league_2v2":0,"current_rank_2v2":82,"current_league_3v3":0,"current_rank_3v3":63,"current_league_4v4":0,"current_rank_4v4":66,"achievement_points":290,"season_games":1,"career_games":280,"portrait":"Unknown59","updated_at":"2014-01-03T18:42:11+00:00","queued":false,"most_played_gametype":"","stats":{"apm":{"avg":53.676660855791},"wpm":{"avg":1.32040768344748}}},"spending_quotient":47.97086169551275,"stats":{"entity_id":13182321,"highest_league":0,"base_2":271,"miningbase_2":271,"base_3":1116,"miningbase_3":1116,"saturation_1":480,"mineral_saturation_1":410,"gas_saturation_1":510,"worker22x_1":450,"saturation_2":720,"mineral_saturation_2":610,"gas_saturation_2":710,"worker22x_2":660,"saturation_3":null,"mineral_saturation_3":null,"gas_saturation_3":null,"worker22x_3":null}},{"id":13182322,"wpm":null,"apm":67.7803203661327,"spending_skill":0.718472525281505,"win":true,"race":"Z","team":2,"color":"0042FF","race_macro":0.491186778889202,"sat_1_skill":0.0,"sat_2_skill":0.0,"sat_3_skill":null,"saturation_skill":0.0,"max_creep_spread":4.16,"identity":{"id":1351795,"type":"ESDB::Sc2::Identity","name":"Theck","provider_id":null,"provider_ident":null,"gateway":"eu","subregion":1,"bnet_id":2023313,"matches_count":3,"hours_played":0.9169444444444445,"profile_url":"http://eu.battle.net/sc2/en/profile/2023313/1/Theck/","most_played_race":"z","current_highest_type":"1v1","current_highest_league":1,"current_highest_leaguerank":24,"current_league_1v1":1,"current_rank_1v1":24,"current_league_2v2":0,"current_rank_2v2":91,"current_league_3v3":0,"current_rank_3v3":72,"current_league_4v4":null,"current_rank_4v4":null,"achievement_points":1035,"season_games":14,"career_games":459,"portrait":"Hydralisk","updated_at":"2013-08-30T23:01:50+00:00","queued":false,"most_played_gametype":"","stats":{"apm":{"avg":60.8518305947978},"wpm":{"avg":null}}},"spending_quotient":51.293155503949976,"stats":{"entity_id":13182322,"highest_league":0,"base_2":284,"miningbase_2":284,"base_3":768,"miningbase_3":null,"saturation_1":460,"mineral_saturation_1":380,"gas_saturation_1":450,"worker22x_1":440,"saturation_2":620,"mineral_saturation_2":620,"gas_saturation_2":720,"worker22x_2":600,"saturation_3":null,"mineral_saturation_3":null,"gas_saturation_3":null,"worker22x_3":null}}]},{"id":4420260,"ended_at":"2013-11-27T18:59:55+00:00","winning_team":2,"category":"Ladder","game_type":"1v1","average_league":0,"duration_seconds":1688,"release_string":"2.0.11.26825","replays_count":1,"summaries_count":0,"expansion":1,"cobrand":null,"map_name":"Star Station TE","entities":[{"id":13182323,"wpm":null,"apm":71.0095011876485,"spending_skill":1.94997885117666,"win":false,"race":"T","team":1,"color":"B4141E","race_macro":0.977346745889846,"sat_1_skill":0.0,"sat_2_skill":0.0,"sat_3_skill":0.0,"saturation_skill":0.0,"max_creep_spread":null,"identity":{"id":1412488,"type":"ESDB::Sc2::Identity","name":"RanbowXy","provider_id":null,"provider_ident":null,"gateway":"eu","subregion":1,"bnet_id":3469155,"matches_count":7,"hours_played":2.680277777777778,"profile_url":"http://eu.battle.net/sc2/en/profile/3469155/1/RanbowXy/","most_played_race":"t","current_highest_type":"1v1","current_highest_league":1,"current_highest_leaguerank":1,"current_league_1v1":1,"current_rank_1v1":1,"current_league_2v2":0,"current_rank_2v2":6,"current_league_3v3":0,"current_rank_3v3":71,"current_league_4v4":0,"current_rank_4v4":81,"achievement_points":790,"season_games":228,"career_games":983,"portrait":"Unknown51","updated_at":"2013-12-22T17:49:46+00:00","queued":false,"most_played_gametype":"","stats":{"apm":{"avg":63.4298224498038},"wpm":{"avg":null}}},"spending_quotient":52.80955398898084,"stats":{"entity_id":13182323,"highest_league":0,"base_2":279,"miningbase_2":279,"base_3":1548,"miningbase_3":1548,"saturation_1":360,"mineral_saturation_1":340,"gas_saturation_1":470,"worker22x_1":430,"saturation_2":580,"mineral_saturation_2":560,"gas_saturation_2":null,"worker22x_2":null,"saturation_3":null,"mineral_saturation_3":null,"gas_saturation_3":null,"worker22x_3":null}},{"id":13182324,"wpm":null,"apm":88.3649289099526,"spending_skill":1.8487523490265,"win":true,"race":"Z","team":2,"color":"0042FF","race_macro":0.522710225852154,"sat_1_skill":4.0,"sat_2_skill":5.0,"sat_3_skill":0.0,"saturation_skill":0.0,"max_creep_spread":7.96610169491525,"identity":{"id":1161842,"type":"ESDB::Sc2::Identity","name":"Baconator","provider_id":null,"provider_ident":null,"gateway":"eu","subregion":1,"bnet_id":3640351,"matches_count":256,"hours_played":87.88027777777778,"profile_url":"http://eu.battle.net/sc2/en/profile/3640351/1/Baconator/","most_played_race":"z","current_highest_type":"1v1","current_highest_league":1,"current_highest_leaguerank":91,"current_league_1v1":1,"current_rank_1v1":91,"current_league_2v2":0,"current_rank_2v2":82,"current_league_3v3":0,"current_rank_3v3":63,"current_league_4v4":0,"current_rank_4v4":66,"achievement_points":290,"season_games":1,"career_games":280,"portrait":"Unknown59","updated_at":"2014-01-03T18:42:11+00:00","queued":false,"most_played_gametype":"","stats":{"apm":{"avg":53.676660855791},"wpm":{"avg":1.32040768344748}}},"spending_quotient":52.05025208612835,"stats":{"entity_id":13182324,"highest_league":0,"base_2":236,"miningbase_2":236,"base_3":614,"miningbase_3":614,"saturation_1":330,"mineral_saturation_1":240,"gas_saturation_1":560,"worker22x_1":310,"saturation_2":720,"mineral_saturation_2":440,"gas_saturation_2":1370,"worker22x_2":710,"saturation_3":null,"mineral_saturation_3":null,"gas_saturation_3":null,"worker22x_3":null}}]},{"id":4398261,"ended_at":"2013-11-22T18:36:07+00:00","winning_team":1,"category":"Ladder","game_type":"1v1","average_league":1,"duration_seconds":1572,"release_string":"2.0.11.26825","replays_count":1,"summaries_count":0,"expansion":1,"cobrand":null,"map_name":"Alterzim Stronghold TE","entities":[{"id":13124323,"wpm":null,"apm":46.6793893129771,"spending_skill":0.132875735935105,"win":true,"race":"P","team":1,"color":"B4141E","race_macro":0.476684450236908,"sat_1_skill":1.0,"sat_2_skill":5.0,"sat_3_skill":1.0,"saturation_skill":1.0,"max_creep_spread":null,"identity":{"id":1289724,"type":"ESDB::Sc2::Identity","name":"Aterro","provider_id":null,"provider_ident":null,"gateway":"eu","subregion":2,"bnet_id":615473,"matches_count":63,"hours_played":25.24138888888889,"profile_url":"http://eu.battle.net/sc2/en/profile/615473/2/Aterro/","most_played_race":"p","current_highest_type":"1v1","current_highest_league":1,"current_highest_leaguerank":77,"current_league_1v1":1,"current_rank_1v1":77,"current_league_2v2":1,"current_rank_2v2":26,"current_league_3v3":null,"current_rank_3v3":null,"current_league_4v4":null,"current_rank_4v4":null,"achievement_points":2390,"season_games":2,"career_games":393,"portrait":"Unknown23","updated_at":"2013-11-22T22:11:29+00:00","queued":false,"most_played_gametype":"","stats":{"apm":{"avg":42.6801673146442},"wpm":{"avg":1.0235825388861}}},"spending_quotient":46.18992797830592,"stats":{"entity_id":13124323,"highest_league":7,"base_2":276,"miningbase_2":276,"base_3":522,"miningbase_3":522,"saturation_1":350,"mineral_saturation_1":250,"gas_saturation_1":370,"worker22x_1":310,"saturation_2":560,"mineral_saturation_2":470,"gas_saturation_2":560,"worker22x_2":490,"saturation_3":710,"mineral_saturation_3":680,"gas_saturation_3":720,"worker22x_3":650}},{"id":13124325,"wpm":null,"apm":63.3587786259542,"spending_skill":1.65751951774593,"win":false,"race":"Z","team":2,"color":"0042FF","race_macro":0.525366984290497,"sat_1_skill":0.0,"sat_2_skill":3.0,"sat_3_skill":0.0,"saturation_skill":0.0,"max_creep_spread":10.06,"identity":{"id":1161842,"type":"ESDB::Sc2::Identity","name":"Baconator","provider_id":null,"provider_ident":null,"gateway":"eu","subregion":1,"bnet_id":3640351,"matches_count":256,"hours_played":87.88027777777778,"profile_url":"http://eu.battle.net/sc2/en/profile/3640351/1/Baconator/","most_played_race":"z","current_highest_type":"1v1","current_highest_league":1,"current_highest_leaguerank":91,"current_league_1v1":1,"current_rank_1v1":91,"current_league_2v2":0,"current_rank_2v2":82,"current_league_3v3":0,"current_rank_3v3":63,"current_league_4v4":0,"current_rank_4v4":66,"achievement_points":290,"season_games":1,"career_games":280,"portrait":"Unknown59","updated_at":"2014-01-03T18:42:11+00:00","queued":false,"most_played_gametype":"","stats":{"apm":{"avg":53.676660855791},"wpm":{"avg":1.32040768344748}}},"spending_quotient":51.98981160549718,"stats":{"entity_id":13124325,"highest_league":0,"base_2":264,"miningbase_2":264,"base_3":523,"miningbase_3":523,"saturation_1":350,"mineral_saturation_1":320,"gas_saturation_1":350,"worker22x_1":320,"saturation_2":570,"mineral_saturation_2":480,"gas_saturation_2":550,"worker22x_2":550,"saturation_3":null,"mineral_saturation_3":null,"gas_saturation_3":850,"worker22x_3":null}}]},{"id":4393705,"ended_at":"2013-11-21T19:35:05+00:00","winning_team":2,"category":"Ladder","game_type":"1v1","average_league":1,"duration_seconds":1371,"release_string":"2.0.11.26825","replays_count":1,"summaries_count":0,"expansion":1,"cobrand":null,"map_name":"Alterzim Stronghold TE","entities":[{"id":13112341,"wpm":null,"apm":36.8859649122807,"spending_skill":0.0,"win":false,"race":"P","team":1,"color":"B4141E","race_macro":0.601905406803412,"sat_1_skill":0.0,"sat_2_skill":5.0,"sat_3_skill":null,"saturation_skill":0.0,"max_creep_spread":null,"identity":{"id":1308975,"type":"ESDB::Sc2::Identity","name":"bigFob","provider_id":null,"provider_ident":null,"gateway":"eu","subregion":1,"bnet_id":1373227,"matches_count":null,"hours_played":0.0,"profile_url":"http://eu.battle.net/sc2/en/profile/1373227/1/bigFob/","most_played_race":"p","current_highest_type":"1v1","current_highest_league":0,"current_highest_leaguerank":11,"current_league_1v1":0,"current_rank_1v1":11,"current_league_2v2":null,"current_rank_2v2":null,"current_league_3v3":null,"current_rank_3v3":null,"current_league_4v4":null,"current_rank_4v4":null,"achievement_points":2455,"season_games":21,"career_games":1167,"portrait":"Kachinsky","updated_at":"2013-11-21T19:36:25+00:00","queued":false,"most_played_gametype":"","stats":{"apm":{"avg":null},"wpm":{"avg":null}}},"spending_quotient":40.43061570740562,"stats":{"entity_id":13112341,"highest_league":0,"base_2":479,"miningbase_2":479,"base_3":null,"miningbase_3":null,"saturation_1":340,"mineral_saturation_1":340,"gas_saturation_1":250,"worker22x_1":300,"saturation_2":670,"mineral_saturation_2":600,"gas_saturation_2":700,"worker22x_2":590,"saturation_3":null,"mineral_saturation_3":null,"gas_saturation_3":null,"worker22x_3":null}},{"id":13112342,"wpm":null,"apm":73.9168490153173,"spending_skill":1.72772844784272,"win":true,"race":"Z","team":2,"color":"0042FF","race_macro":0.638382763665381,"sat_1_skill":0.0,"sat_2_skill":0.0,"sat_3_skill":0.0,"saturation_skill":0.0,"max_creep_spread":9.61,"identity":{"id":1161842,"type":"ESDB::Sc2::Identity","name":"Baconator","provider_id":null,"provider_ident":null,"gateway":"eu","subregion":1,"bnet_id":3640351,"matches_count":256,"hours_played":87.88027777777778,"profile_url":"http://eu.battle.net/sc2/en/profile/3640351/1/Baconator/","most_played_race":"z","current_highest_type":"1v1","current_highest_league":1,"current_highest_leaguerank":91,"current_league_1v1":1,"current_rank_1v1":91,"current_league_2v2":0,"current_rank_2v2":82,"current_league_3v3":0,"current_rank_3v3":63,"current_league_4v4":0,"current_rank_4v4":66,"achievement_points":290,"season_games":1,"career_games":280,"portrait":"Unknown59","updated_at":"2014-01-03T18:42:11+00:00","queued":false,"most_played_gametype":"","stats":{"apm":{"avg":53.676660855791},"wpm":{"avg":1.32040768344748}}},"spending_quotient":56.748027536752176,"stats":{"entity_id":13112342,"highest_league":0,"base_2":271,"miningbase_2":271,"base_3":643,"miningbase_3":643,"saturation_1":360,"mineral_saturation_1":330,"gas_saturation_1":380,"worker22x_1":340,"saturation_2":650,"mineral_saturation_2":600,"gas_saturation_2":640,"worker22x_2":640,"saturation_3":null,"mineral_saturation_3":null,"gas_saturation_3":null,"worker22x_3":null}}]},{"id":4393706,"ended_at":"2013-11-21T19:16:27+00:00","winning_team":1,"category":"Ladder","game_type":"1v1","average_league":0,"duration_seconds":1491,"release_string":"2.0.11.26825","replays_count":1,"summaries_count":0,"expansion":1,"cobrand":null,"map_name":"Star Station TE","entities":[{"id":13112343,"wpm":null,"apm":73.3199195171026,"spending_skill":3.33503369761228,"win":true,"race":"Z","team":1,"color":"B4141E","race_macro":0.618506885721189,"sat_1_skill":0.0,"sat_2_skill":0.0,"sat_3_skill":0.0,"saturation_skill":0.0,"max_creep_spread":9.24576271186441,"identity":{"id":1161842,"type":"ESDB::Sc2::Identity","name":"Baconator","provider_id":null,"provider_ident":null,"gateway":"eu","subregion":1,"bnet_id":3640351,"matches_count":256,"hours_played":87.88027777777778,"profile_url":"http://eu.battle.net/sc2/en/profile/3640351/1/Baconator/","most_played_race":"z","current_highest_type":"1v1","current_highest_league":1,"current_highest_leaguerank":91,"current_league_1v1":1,"current_rank_1v1":91,"current_league_2v2":0,"current_rank_2v2":82,"current_league_3v3":0,"current_rank_3v3":63,"current_league_4v4":0,"current_rank_4v4":66,"achievement_points":290,"season_games":1,"career_games":280,"portrait":"Unknown59","updated_at":"2014-01-03T18:42:11+00:00","queued":false,"most_played_gametype":"","stats":{"apm":{"avg":53.676660855791},"wpm":{"avg":1.32040768344748}}},"spending_quotient":64.04838393412274,"stats":{"entity_id":13112343,"highest_league":0,"base_2":271,"miningbase_2":271,"base_3":673,"miningbase_3":673,"saturation_1":330,"mineral_saturation_1":290,"gas_saturation_1":460,"worker22x_1":330,"saturation_2":860,"mineral_saturation_2":740,"gas_saturation_2":790,"worker22x_2":850,"saturation_3":null,"mineral_saturation_3":null,"gas_saturation_3":null,"worker22x_3":null}},{"id":13112344,"wpm":null,"apm":24.4832214765101,"spending_skill":0.0,"win":false,"race":"P","team":2,"color":"0042FF","race_macro":0.3032715417567,"sat_1_skill":2.0,"sat_2_skill":null,"sat_3_skill":null,"saturation_skill":2.0,"max_creep_spread":null,"identity":{"id":1420263,"type":"ESDB::Sc2::Identity","name":"Mysterium","provider_id":null,"provider_ident":null,"gateway":"eu","subregion":1,"bnet_id":4279095,"matches_count":null,"hours_played":0.0,"profile_url":"http://eu.battle.net/sc2/en/profile/4279095/1/Mysterium/","most_played_race":"t","current_highest_type":null,"current_highest_league":null,"current_highest_leaguerank":null,"current_league_1v1":null,"current_rank_1v1":null,"current_league_2v2":null,"current_rank_2v2":null,"current_league_3v3":null,"current_rank_3v3":null,"current_league_4v4":null,"current_rank_4v4":null,"achievement_points":1660,"season_games":11,"career_games":141,"portrait":"Unknown1","updated_at":"2013-11-21T19:36:25+00:00","queued":false,"most_played_gametype":"","stats":{"apm":{"avg":null},"wpm":{"avg":null}}},"spending_quotient":24.823914281413977,"stats":{"entity_id":13112344,"highest_league":7,"base_2":null,"miningbase_2":null,"base_3":null,"miningbase_3":null,"saturation_1":310,"mineral_saturation_1":240,"gas_saturation_1":270,"worker22x_1":250,"saturation_2":null,"mineral_saturation_2":null,"gas_saturation_2":null,"worker22x_2":null,"saturation_3":null,"mineral_saturation_3":null,"gas_saturation_3":null,"worker22x_3":null}}]},{"id":4389857,"ended_at":"2013-11-20T19:02:42+00:00","winning_team":1,"category":"Ladder","game_type":"1v1","average_league":0,"duration_seconds":1252,"release_string":"2.0.11.26825","replays_count":1,"summaries_count":0,"expansion":1,"cobrand":null,"map_name":"Derelict Watcher TE","entities":[{"id":13102826,"wpm":null,"apm":71.0702875399361,"spending_skill":0.0,"win":true,"race":"Z","team":1,"color":"B4141E","race_macro":0.488483031211667,"sat_1_skill":5.0,"sat_2_skill":0.0,"sat_3_skill":0.0,"saturation_skill":0.0,"max_creep_spread":8.97058823529412,"identity":{"id":1161842,"type":"ESDB::Sc2::Identity","name":"Baconator","provider_id":null,"provider_ident":null,"gateway":"eu","subregion":1,"bnet_id":3640351,"matches_count":256,"hours_played":87.88027777777778,"profile_url":"http://eu.battle.net/sc2/en/profile/3640351/1/Baconator/","most_played_race":"z","current_highest_type":"1v1","current_highest_league":1,"current_highest_leaguerank":91,"current_league_1v1":1,"current_rank_1v1":91,"current_league_2v2":0,"current_rank_2v2":82,"current_league_3v3":0,"current_rank_3v3":63,"current_league_4v4":0,"current_rank_4v4":66,"achievement_points":290,"season_games":1,"career_games":280,"portrait":"Unknown59","updated_at":"2014-01-03T18:42:11+00:00","queued":false,"most_played_gametype":"","stats":{"apm":{"avg":53.676660855791},"wpm":{"avg":1.32040768344748}}},"spending_quotient":40.12152644844926,"stats":{"entity_id":13102826,"highest_league":0,"base_2":237,"miningbase_2":237,"base_3":727,"miningbase_3":727,"saturation_1":340,"mineral_saturation_1":230,"gas_saturation_1":920,"worker22x_1":310,"saturation_2":960,"mineral_saturation_2":960,"gas_saturation_2":940,"worker22x_2":940,"saturation_3":null,"mineral_saturation_3":null,"gas_saturation_3":null,"worker22x_3":null}},{"id":13102827,"wpm":null,"apm":49.375,"spending_skill":0.0,"win":false,"race":"T","team":2,"color":"0042FF","race_macro":1.0,"sat_1_skill":0.0,"sat_2_skill":0.0,"sat_3_skill":0.0,"saturation_skill":0.0,"max_creep_spread":null,"identity":{"id":1304698,"type":"ESDB::Sc2::Identity","name":"Angsaar","provider_id":null,"provider_ident":null,"gateway":"eu","subregion":1,"bnet_id":3888065,"matches_count":null,"hours_played":0.0,"profile_url":"http://eu.battle.net/sc2/en/profile/3888065/1/Angsaar/","most_played_race":"t","current_highest_type":"4v4","current_highest_league":2,"current_highest_leaguerank":89,"current_league_1v1":1,"current_rank_1v1":15,"current_league_2v2":1,"current_rank_2v2":10,"current_league_3v3":null,"current_rank_3v3":null,"current_league_4v4":2,"current_rank_4v4":89,"achievement_points":1870,"season_games":56,"career_games":416,"portrait":"Unknown5","updated_at":"2013-11-21T22:06:30+00:00","queued":false,"most_played_gametype":"","stats":{"apm":{"avg":null},"wpm":{"avg":null}}},"spending_quotient":44.569367298861096,"stats":{"entity_id":13102827,"highest_league":0,"base_2":362,"miningbase_2":391,"base_3":null,"miningbase_3":869,"saturation_1":350,"mineral_saturation_1":290,"gas_saturation_1":390,"worker22x_1":380,"saturation_2":null,"mineral_saturation_2":640,"gas_saturation_2":null,"worker22x_2":null,"saturation_3":null,"mineral_saturation_3":null,"gas_saturation_3":null,"worker22x_3":null}}]},{"id":4380720,"ended_at":"2013-11-18T19:47:06+00:00","winning_team":2,"category":"Ladder","game_type":"1v1","average_league":1,"duration_seconds":835,"release_string":"2.0.11.26825","replays_count":1,"summaries_count":0,"expansion":1,"cobrand":null,"map_name":"Polar Night LE","entities":[{"id":13079106,"wpm":null,"apm":91.1538461538461,"spending_skill":0.825283135771069,"win":false,"race":"Z","team":1,"color":"B4141E","race_macro":0.657807796784377,"sat_1_skill":3.0,"sat_2_skill":0.0,"sat_3_skill":null,"saturation_skill":0.0,"max_creep_spread":4.69879518072289,"identity":{"id":127423,"type":"ESDB::Sc2::Identity","name":"Fluffybutt","provider_id":null,"provider_ident":null,"gateway":"eu","subregion":1,"bnet_id":553891,"matches_count":9,"hours_played":2.0533333333333332,"profile_url":"http://eu.battle.net/sc2/en/profile/553891/1/Fluffybutt/","most_played_race":"t","current_highest_type":"1v1","current_highest_league":2,"current_highest_leaguerank":99,"current_league_1v1":2,"current_rank_1v1":99,"current_league_2v2":1,"current_rank_2v2":36,"current_league_3v3":1,"current_rank_3v3":84,"current_league_4v4":1,"current_rank_4v4":3,"achievement_points":4960,"season_games":705,"career_games":4900,"portrait":"Cade","updated_at":"2014-01-01T18:19:32+00:00","queued":false,"most_played_gametype":"","stats":{"apm":{"avg":45.38437519565},"wpm":{"avg":3.76657168683932}}},"spending_quotient":59.26661780272519,"stats":{"entity_id":13079106,"highest_league":2,"base_2":430,"miningbase_2":430,"base_3":null,"miningbase_3":null,"saturation_1":null,"mineral_saturation_1":280,"gas_saturation_1":610,"worker22x_1":840,"saturation_2":null,"mineral_saturation_2":null,"gas_saturation_2":null,"worker22x_2":null,"saturation_3":null,"mineral_saturation_3":null,"gas_saturation_3":null,"worker22x_3":null}},{"id":13079107,"wpm":null,"apm":54.9700598802395,"spending_skill":0.771790995007598,"win":true,"race":"Z","team":2,"color":"0042FF","race_macro":0.66386215639947,"sat_1_skill":0.0,"sat_2_skill":3.0,"sat_3_skill":null,"saturation_skill":0.0,"max_creep_spread":6.33734939759036,"identity":{"id":1161842,"type":"ESDB::Sc2::Identity","name":"Baconator","provider_id":null,"provider_ident":null,"gateway":"eu","subregion":1,"bnet_id":3640351,"matches_count":256,"hours_played":87.88027777777778,"profile_url":"http://eu.battle.net/sc2/en/profile/3640351/1/Baconator/","most_played_race":"z","current_highest_type":"1v1","current_highest_league":1,"current_highest_leaguerank":91,"current_league_1v1":1,"current_rank_1v1":91,"current_league_2v2":0,"current_rank_2v2":82,"current_league_3v3":0,"current_rank_3v3":63,"current_league_4v4":0,"current_rank_4v4":66,"achievement_points":290,"season_games":1,"career_games":280,"portrait":"Unknown59","updated_at":"2014-01-03T18:42:11+00:00","queued":false,"most_played_gametype":"","stats":{"apm":{"avg":53.676660855791},"wpm":{"avg":1.32040768344748}}},"spending_quotient":58.94272913118414,"stats":{"entity_id":13079107,"highest_league":0,"base_2":272,"miningbase_2":272,"base_3":null,"miningbase_3":null,"saturation_1":400,"mineral_saturation_1":370,"gas_saturation_1":660,"worker22x_1":380,"saturation_2":null,"mineral_saturation_2":560,"gas_saturation_2":null,"worker22x_2":null,"saturation_3":null,"mineral_saturation_3":null,"gas_saturation_3":null,"worker22x_3":null}}]},{"id":4380721,"ended_at":"2013-11-18T19:34:27+00:00","winning_team":1,"category":"Ladder","game_type":"1v1","average_league":1,"duration_seconds":1692,"release_string":"2.0.11.26825","replays_count":1,"summaries_count":0,"expansion":1,"cobrand":null,"map_name":"Star Station TE","entities":[{"id":13079108,"wpm":null,"apm":50.0709219858156,"spending_skill":0.256938403353924,"win":true,"race":"P","team":1,"color":"B4141E","race_macro":0.39121074759839,"sat_1_skill":0.0,"sat_2_skill":4.0,"sat_3_skill":0.0,"saturation_skill":0.0,"max_creep_spread":null,"identity":{"id":1183219,"type":"ESDB::Sc2::Identity","name":"Hyyga","provider_id":null,"provider_ident":null,"gateway":"eu","subregion":1,"bnet_id":1084032,"matches_count":5,"hours_played":1.4483333333333333,"profile_url":"http://eu.battle.net/sc2/en/profile/1084032/1/Hyyga/","most_played_race":"z","current_highest_type":"1v1","current_highest_league":1,"current_highest_leaguerank":28,"current_league_1v1":1,"current_rank_1v1":28,"current_league_2v2":null,"current_rank_2v2":null,"current_league_3v3":null,"current_rank_3v3":null,"current_league_4v4":3,"current_rank_4v4":14,"achievement_points":2050,"season_games":154,"career_games":693,"portrait":"Unknown12","updated_at":"2013-12-21T22:33:03+00:00","queued":false,"most_played_gametype":"","stats":{"apm":{"avg":44.0454545454545},"wpm":{"avg":1.57700900461527}}},"spending_quotient":43.581602257447,"stats":{"entity_id":13079108,"highest_league":7,"base_2":424,"miningbase_2":424,"base_3":796,"miningbase_3":796,"saturation_1":430,"mineral_saturation_1":270,"gas_saturation_1":340,"worker22x_1":380,"saturation_2":660,"mineral_saturation_2":660,"gas_saturation_2":590,"worker22x_2":610,"saturation_3":null,"mineral_saturation_3":null,"gas_saturation_3":null,"worker22x_3":null}},{"id":13079110,"wpm":null,"apm":63.6879432624114,"spending_skill":0.0,"win":false,"race":"Z","team":2,"color":"0042FF","race_macro":0.454860225243285,"sat_1_skill":0.0,"sat_2_skill":0.0,"sat_3_skill":0.0,"saturation_skill":0.0,"max_creep_spread":6.61016949152542,"identity":{"id":1161842,"type":"ESDB::Sc2::Identity","name":"Baconator","provider_id":null,"provider_ident":null,"gateway":"eu","subregion":1,"bnet_id":3640351,"matches_count":256,"hours_played":87.88027777777778,"profile_url":"http://eu.battle.net/sc2/en/profile/3640351/1/Baconator/","most_played_race":"z","current_highest_type":"1v1","current_highest_league":1,"current_highest_leaguerank":91,"current_league_1v1":1,"current_rank_1v1":91,"current_league_2v2":0,"current_rank_2v2":82,"current_league_3v3":0,"current_rank_3v3":63,"current_league_4v4":0,"current_rank_4v4":66,"achievement_points":290,"season_games":1,"career_games":280,"portrait":"Unknown59","updated_at":"2014-01-03T18:42:11+00:00","queued":false,"most_played_gametype":"","stats":{"apm":{"avg":53.676660855791},"wpm":{"avg":1.32040768344748}}},"spending_quotient":18.547136506999635,"stats":{"entity_id":13079110,"highest_league":0,"base_2":264,"miningbase_2":264,"base_3":423,"miningbase_3":423,"saturation_1":380,"mineral_saturation_1":330,"gas_saturation_1":430,"worker22x_1":320,"saturation_2":640,"mineral_saturation_2":590,"gas_saturation_2":890,"worker22x_2":630,"saturation_3":null,"mineral_saturation_3":null,"gas_saturation_3":null,"worker22x_3":null}}]},{"id":4380719,"ended_at":"2013-11-18T19:12:56+00:00","winning_team":1,"category":"Ladder","game_type":"1v1","average_league":0,"duration_seconds":1133,"release_string":"2.0.11.26825","replays_count":1,"summaries_count":0,"expansion":1,"cobrand":null,"map_name":"Alterzim Stronghold TE","entities":[{"id":13079104,"wpm":null,"apm":62.5419240953222,"spending_skill":1.31573572682543,"win":true,"race":"Z","team":1,"color":"B4141E","race_macro":0.586214792763911,"sat_1_skill":0.0,"sat_2_skill":0.0,"sat_3_skill":null,"saturation_skill":0.0,"max_creep_spread":3.83,"identity":{"id":1161842,"type":"ESDB::Sc2::Identity","name":"Baconator","provider_id":null,"provider_ident":null,"gateway":"eu","subregion":1,"bnet_id":3640351,"matches_count":256,"hours_played":87.88027777777778,"profile_url":"http://eu.battle.net/sc2/en/profile/3640351/1/Baconator/","most_played_race":"z","current_highest_type":"1v1","current_highest_league":1,"current_highest_leaguerank":91,"current_league_1v1":1,"current_rank_1v1":91,"current_league_2v2":0,"current_rank_2v2":82,"current_league_3v3":0,"current_rank_3v3":63,"current_league_4v4":0,"current_rank_4v4":66,"achievement_points":290,"season_games":1,"career_games":280,"portrait":"Unknown59","updated_at":"2014-01-03T18:42:11+00:00","queued":false,"most_played_gametype":"","stats":{"apm":{"avg":53.676660855791},"wpm":{"avg":1.32040768344748}}},"spending_quotient":55.84961153108637,"stats":{"entity_id":13079104,"highest_league":0,"base_2":274,"miningbase_2":274,"base_3":null,"miningbase_3":null,"saturation_1":340,"mineral_saturation_1":310,"gas_saturation_1":650,"worker22x_1":330,"saturation_2":null,"mineral_saturation_2":null,"gas_saturation_2":null,"worker22x_2":null,"saturation_3":null,"mineral_saturation_3":null,"gas_saturation_3":null,"worker22x_3":null}},{"id":13079105,"wpm":null,"apm":32.9734513274336,"spending_skill":0.0,"win":false,"race":"T","team":2,"color":"0042FF","race_macro":0.563591132245779,"sat_1_skill":0.0,"sat_2_skill":null,"sat_3_skill":null,"saturation_skill":0.0,"max_creep_spread":null,"identity":{"id":228704,"type":"ESDB::Sc2::Identity","name":"Akâ","provider_id":null,"provider_ident":null,"gateway":"eu","subregion":1,"bnet_id":1474421,"matches_count":13,"hours_played":3.7775,"profile_url":"http://eu.battle.net/sc2/en/profile/1474421/1/Ak%C3%A2/","most_played_race":"z","current_highest_type":null,"current_highest_league":null,"current_highest_leaguerank":null,"current_league_1v1":null,"current_rank_1v1":null,"current_league_2v2":null,"current_rank_2v2":null,"current_league_3v3":null,"current_rank_3v3":null,"current_league_4v4":null,"current_rank_4v4":null,"achievement_points":5665,"season_games":354,"career_games":8916,"portrait":"Hybrid Reaver","updated_at":"2013-12-06T23:39:37+00:00","queued":false,"most_played_gametype":"","stats":{"apm":{"avg":39.3234407986306},"wpm":{"avg":0.748354548921724}}},"spending_quotient":50.77858909103563,"stats":{"entity_id":13079105,"highest_league":7,"base_2":null,"miningbase_2":null,"base_3":null,"miningbase_3":null,"saturation_1":null,"mineral_saturation_1":null,"gas_saturation_1":null,"worker22x_1":null,"saturation_2":null,"mineral_saturation_2":null,"gas_saturation_2":null,"worker22x_2":null,"saturation_3":null,"mineral_saturation_3":null,"gas_saturation_3":null,"worker22x_3":null}}]}]}